CHANGELOG.md
LICENSE
youtube_monitor_action/__init__.py
youtube_monitor_action/__main__.py
youtube_monitor_action/_logging_utils.py
youtube_monitor_action-1.0.5.dist-info/entry_points.txt
youtube_monitor_action-1.0.5.dist-info/LICENSE
youtube_monitor_action-1.0.5.dist-info/WHEEL
youtube_monitor_action-1.0.5.dist-info/METADATA
youtube_monitor_action-1.0.5.dist-info/RECORD
