Metadata-Version: 2.1
Name: youtube-monitor-action
Version: 1.0.5
Summary: Monitor for new video on YouTube Channel
Home-page: https://github.com/mshafer1/youtube_monitor_action
License: MIT
Author: mshafer1
Requires-Python: >=3.6.2,<4.0.0
Classifier: License :: OSI Approved :: MIT License
Classifier: Programming Language :: Python :: 3
Classifier: Programming Language :: Python :: 3.10
Classifier: Programming Language :: Python :: 3.7
Classifier: Programming Language :: Python :: 3.8
Classifier: Programming Language :: Python :: 3.9
Requires-Dist: PyYAML (>=5.4.1,<6.0.0)
Requires-Dist: importlib-metadata (>=4.8.1,<5.0.0)
Requires-Dist: requests (>=2.26.0,<3.0.0)
Requires-Dist: xmltodict (>=0.12.0,<0.13.0)
Project-URL: Repository, https://github.com/mshafer1/youtube_monitor_action
